odoo/addons/cron_daylight_saving_time_resistant/README.rst
odoo/addons/cron_daylight_saving_time_resistant/__init__.py
odoo/addons/cron_daylight_saving_time_resistant/__manifest__.py
odoo/addons/cron_daylight_saving_time_resistant/i18n/cron_daylight_saving_time_resistant.pot
odoo/addons/cron_daylight_saving_time_resistant/i18n/es.po
odoo/addons/cron_daylight_saving_time_resistant/i18n/it.po
odoo/addons/cron_daylight_saving_time_resistant/models/__init__.py
odoo/addons/cron_daylight_saving_time_resistant/models/ir_cron.py
odoo/addons/cron_daylight_saving_time_resistant/readme/CONFIGURE.rst
odoo/addons/cron_daylight_saving_time_resistant/readme/CONTRIBUTORS.rst
odoo/addons/cron_daylight_saving_time_resistant/readme/DESCRIPTION.rst
odoo/addons/cron_daylight_saving_time_resistant/static/description/icon.png
odoo/addons/cron_daylight_saving_time_resistant/static/description/index.html
odoo/addons/cron_daylight_saving_time_resistant/tests/__init__.py
odoo/addons/cron_daylight_saving_time_resistant/tests/test_dst.py
odoo/addons/cron_daylight_saving_time_resistant/views/ir_cron_views.xml
odoo_addon_cron_daylight_saving_time_resistant-16.0.1.0.1.dist-info/METADATA
odoo_addon_cron_daylight_saving_time_resistant-16.0.1.0.1.dist-info/WHEEL
odoo_addon_cron_daylight_saving_time_resistant-16.0.1.0.1.dist-info/top_level.txt
odoo_addon_cron_daylight_saving_time_resistant-16.0.1.0.1.dist-info/RECORD
